[
  {
    "id": 1,
    "first_name": "Erkan",
    "last_name": "Öztürk",
    "project_name": "Twitterbeat",
    "phone_number": "546-997-9427",
    "gender": "Male",
    "orders_count": 81,
    "last_order": "2022-08-14T20:42:43Z"
  },
  {
    "id": 2,
    "first_name": "Ricardo",
    "last_name": "Quaresma",
    "project_name": "Youfeed",
    "phone_number": "742-147-4726",
    "gender": "Female",
    "orders_count": 70,
    "last_order": "2022-06-29T00:46:40Z"
  },
  {
    "id": 3,
    "first_name": "Pep",
    "last_name": "Guardiola",
    "project_name": "Dazzlesphere",
    "phone_number": "884-818-1057",
    "gender": "Female",
    "orders_count": 33,
    "last_order": "2023-02-22T08:13:10Z"
  },
  {
    "id": 4,
    "first_name": "Alperen",
    "last_name": "Şengün",
    "project_name": "Topicblab",
    "phone_number": "602-596-7864",
    "gender": "Male",
    "orders_count": 88,
    "last_order": "2022-10-25T00:44:36Z"
  },
  {
    "id": 5,
    "first_name": "Süleyman",
    "last_name": "Seba",
    "project_name": "Kazu",
    "phone_number": "188-819-9470",
    "gender": "Female",
    "orders_count": 18,
    "last_order": "2022-07-24T19:56:14Z"
  },
  {
    "id": 6,
    "first_name": "Hakkı",
    "last_name": "Yeten",
    "project_name": "Tagopia",
    "phone_number": "612-849-8550",
    "gender": "Male",
    "orders_count": 51,
    "last_order": "2023-03-10T00:43:08Z"
  },
  {
    "id": 7,
    "first_name": "Feyyyaz",
    "last_name": "Uçar",
    "project_name": "Abata",
    "phone_number": "960-651-7925",
    "gender": "Male",
    "orders_count": 70,
    "last_order": "2022-10-20T00:27:55Z"
  },
  {
    "id": 8,
    "first_name": "Metin",
    "last_name": "Tekin",
    "project_name": "Edgewire",
    "phone_number": "941-155-4071",
    "gender": "Male",
    "orders_count": 71,
    "last_order": "2022-09-18T07:49:26Z"
  },
  {
    "id": 9,
    "first_name": "Fani",
    "last_name": "Madida",
    "project_name": "Plambee",
    "phone_number": "667-722-1497",
    "gender": "Female",
    "orders_count": 49,
    "last_order": "2023-01-17T00:15:57Z"
  },
  {
    "id": 10,
    "first_name": "Mario",
    "last_name": "Gomez",
    "project_name": "Skalith",
    "phone_number": "324-350-8913",
    "gender": "Male",
    "orders_count": 93,
    "last_order": "2023-03-03T09:44:22Z"
  }
]
